lazyk8s/__init__.py
lazyk8s/app.py
lazyk8s/config.py
lazyk8s/gui.py
lazyk8s/k8s_client.py
lazyk8s/main.py
lazyk8s/helpers/formatHelper.py
lazyk8s-0.2.6.dist-info/METADATA
lazyk8s-0.2.6.dist-info/WHEEL
lazyk8s-0.2.6.dist-info/entry_points.txt
lazyk8s-0.2.6.dist-info/top_level.txt
lazyk8s-0.2.6.dist-info/RECORD
